aprendepython/__init__.py
aprendepython/config.py
aprendepython/intro.py
aprendepython/menu.py
aprendepython/utils.py
aprendepython/content/__init__.py
aprendepython/content/lesson_00_intro.py
aprendepython/content/lesson_01_numerics.py
aprendepython/content/lesson_02_strings.py
aprendepython/content/lesson_03_booleans.py
aprendepython/content/lesson_04_arithmetic_ops.py
aprendepython/content/lesson_05_relational_ops.py
aprendepython/content/lesson_06_logical_ops.py
aprendepython/content/lesson_07_lists.py
aprendepython/content/lesson_08_tuples.py
aprendepython/content/lesson_09_dicts.py
aprendepython/content/lesson_10_conditionals.py
aprendepython/content/lesson_11_loops.py
aprendepython/content/lesson_12_functions.py
aprendepython/content/lesson_13_classes.py
aprendepython/models/__init__.py
aprendepython/models/exercise.py
aprendepython/models/lesson.py
aprendepython-1.0.1.dist-info/LICENSE
aprendepython-1.0.1.dist-info/METADATA
aprendepython-1.0.1.dist-info/WHEEL
aprendepython-1.0.1.dist-info/top_level.txt
aprendepython-1.0.1.dist-info/RECORD
