Metadata-Version: 2.1
Name: aprendepython
Version: 1.0.1
Summary: Librería interactiva para aprender los fundamentos de Python
Home-page: https://github.com/OscarM3615/aprendepython/
Author: Óscar Miranda
Author-email: oscarmiranda3615@gmail.com
License: MIT
Keywords: python,curso,fundamentos
Classifier: Environment :: Console
Classifier: Intended Audience :: Information Technology
Classifier: License :: OSI Approved :: MIT License
Classifier: Natural Language :: Spanish
Classifier: Operating System :: OS Independent
Classifier: Programming Language :: Python :: 3.7
Requires-Python: >=3.7
License-File: LICENSE
Requires-Dist: markdown-it-py ==3.0.0
Requires-Dist: mdurl ==0.1.2
Requires-Dist: platformdirs ==3.9.1
Requires-Dist: Pygments ==2.15.1
Requires-Dist: rich ==13.4.2
